medizum/__init__.py
medizum/medizum.py
medizum-0.0.3.dist-info/LICENSE
medizum-0.0.3.dist-info/METADATA
medizum-0.0.3.dist-info/WHEEL
medizum-0.0.3.dist-info/top_level.txt
medizum-0.0.3.dist-info/RECORD
