Metadata-Version: 2.1
Name: medizum
Version: 0.0.3
Summary: Pacote para gerar dados simples.
Home-page: https://github.com/taotamat/medizum
Author: Matheus Victor, Vinicius Dias
Author-email: matheusvictorufpi@gmail.com
License: UNKNOWN
Platform: UNKNOWN
Classifier: Programming Language :: Python :: 3
Classifier: License :: OSI Approved :: MIT License
Classifier: Operating System :: OS Independent
Requires-Python: >=3.8
License-File: LICENSE
Requires-Dist: pandas (>=1.2.4)
Requires-Dist: Pillow (>=7.0.0)
